MANIFEST.in
README.rst
setup.cfg
setup.py
src/banner/__init__.py
src/banner/admin.py
src/banner/models.py
src/banner/utils.py
src/banner/locale/ru/LC_MESSAGES/django.mo
src/banner/locale/ru/LC_MESSAGES/django.po
src/banner/migrations/0001_initial.py
src/banner/migrations/0002_auto__chg_field_banner_link.py
src/banner/migrations/0003_auto__chg_field_banner_image.py
src/banner/migrations/0004_auto__add_alternativeimage.py
src/banner/migrations/__init__.py
src/banner/templates/banner_source.html
src/banner/templatetags/__init__.py
src/banner/templatetags/banner_tags.py
src/django_banner_simple.egg-info/PKG-INFO
src/django_banner_simple.egg-info/SOURCES.txt
src/django_banner_simple.egg-info/dependency_links.txt
src/django_banner_simple.egg-info/requires.txt
src/django_banner_simple.egg-info/top_level.txt
src/django_banner_simple.egg-info/zip-safe