Metadata-Version: 1.1
Name: django-banner-simple
Version: 0.1
Summary: Simple banner system
Home-page: https://github.com/Arpaso/django-banner-simple
Author: Arpaso
Author-email: arvid@arpaso.com
License: UNKNOWN
Download-URL: https://github.com/Arpaso/django-banner-simple/tarball/0.1
Platform: UNKNOWN
Classifier: Framework :: Django
Classifier: Intended Audience :: Developers
Classifier: Intended Audience :: System Administrators
Classifier: Operating System :: OS Independent
Classifier: Topic :: Software Development
